FindArea/FindArea.py
FindArea/__init__.py
FindArea/tests.py
AreaFinding-0.1.dist-info/METADATA
AreaFinding-0.1.dist-info/WHEEL
AreaFinding-0.1.dist-info/top_level.txt
AreaFinding-0.1.dist-info/RECORD
