Metadata-Version: 2.1
Name: AreaFinding
Version: 0.1
Summary: Find are of different figures
Home-page: https://github.com/susmp/test_task.git
Author: Pavlov M
Author-email: mspavlovhse@gmail.com
License: MIT
